__init__.py
frenet_system_creator/__init__.py
frenet_system_creator/common.py
frenet_system_creator/frenet_system.py
frenet_system_creator-0.3.0.dist-info/licenses/LICENSE
frenet_system_creator-0.3.0.dist-info/METADATA
frenet_system_creator-0.3.0.dist-info/WHEEL
frenet_system_creator-0.3.0.dist-info/top_level.txt
frenet_system_creator-0.3.0.dist-info/RECORD
