Metadata-Version: 2.4
Name: frenet-system-creator
Version: 0.3.0
Summary: Utilities for converting between Cartesian and Frenet frames
Author-email: Delvin Yang <jyang512@connect.hkust-gz.edu.cn>
License: MIT
Project-URL: Homepage, https://github.com/DelvinYang/
Requires-Python: >=3.8
License-File: LICENSE
Requires-Dist: numpy
Requires-Dist: scipy
Dynamic: license-file
